{
  "video_id": "20250417_0840_color_right_clipped",
  "view": "right",
  "view_start": 0,
  "view_end": 4227,
  "segments": [
    {
      "id": 0,
      "label": "start_angle_grinder_assembly",
      "has_anomaly": false,
      "meta_activity": "none",
      "f_start": 0,
      "f_end": 54
    },
    {
      "id": 1,
      "label": "unscrew_anti_vibration_handle",
      "has_anomaly": false,
      "meta_activity": "none",
      "f_start": 55,
      "f_end": 221
    },
    {
      "id": 2,
      "label": "store_anti_vibration_handle",
      "has_anomaly": false,
      "meta_activity": "none",
      "f_start": 222,
      "f_end": 249
    },
    {
      "id": 3,
      "label": "remove_locking_lever_assembly",
      "has_anomaly": false,
      "meta_activity": "none",
      "f_start": 250,
      "f_end": 593
    },
    {
      "id": 4,
      "label": "null",
      "has_anomaly": false,
      "meta_activity": "none",
      "f_start": 594,
      "f_end": 611
    },
    {
      "id": 5,
      "label": "remove_locking_lever_assembly",
      "has_anomaly": false,
      "meta_activity": "none",
      "f_start": 612,
      "f_end": 643
    },
    {
      "id": 6,
      "label": "store_locking_lever_assembly",
      "has_anomaly": false,
      "meta_activity": "none",
      "f_start": 644,
      "f_end": 756
    },
    {
      "id": 7,
      "label": "extract_bearing_plate_assembly",
      "has_anomaly": false,
      "meta_activity": "none",
      "f_start": 757,
      "f_end": 1239
    },
    {
      "id": 8,
      "label": "store_bearing_plate_assembly",
      "has_anomaly": false,
      "meta_activity": "none",
      "f_start": 1240,
      "f_end": 1268
    },
    {
      "id": 9,
      "label": "extract_bearing_plate_assembly",
      "has_anomaly": false,
      "meta_activity": "none",
      "f_start": 1269,
      "f_end": 1808
    },
    {
      "id": 10,
      "label": "store_bearing_plate_assembly",
      "has_anomaly": false,
      "meta_activity": "none",
      "f_start": 1809,
      "f_end": 1853
    },
    {
      "id": 11,
      "label": "null",
      "has_anomaly": false,
      "meta_activity": "none",
      "f_start": 1854,
      "f_end": 1882
    },
    {
      "id": 12,
      "label": "detach_adapter_plate",
      "has_anomaly": false,
      "meta_activity": "none",
      "f_start": 1883,
      "f_end": 2075
    },
    {
      "id": 13,
      "label": "store_tool",
      "has_anomaly": false,
      "meta_activity": "none",
      "f_start": 2076,
      "f_end": 2102
    },
    {
      "id": 14,
      "label": "detach_adapter_plate",
      "has_anomaly": false,
      "meta_activity": "none",
      "f_start": 2103,
      "f_end": 2701
    },
    {
      "id": 15,
      "label": "store_adapter_plate",
      "has_anomaly": false,
      "meta_activity": "none",
      "f_start": 2702,
      "f_end": 2741
    },
    {
      "id": 16,
      "label": "detach_adapter_plate",
      "has_anomaly": false,
      "meta_activity": "none",
      "f_start": 2742,
      "f_end": 3072
    },
    {
      "id": 17,
      "label": "null",
      "has_anomaly": false,
      "meta_activity": "none",
      "f_start": 3073,
      "f_end": 3089
    },
    {
      "id": 18,
      "label": "detach_adapter_plate",
      "has_anomaly": false,
      "meta_activity": "none",
      "f_start": 3090,
      "f_end": 3156
    },
    {
      "id": 19,
      "label": "store_adapter_plate",
      "has_anomaly": false,
      "meta_activity": "none",
      "f_start": 3157,
      "f_end": 3202
    },
    {
      "id": 20,
      "label": "null",
      "has_anomaly": false,
      "meta_activity": "none",
      "f_start": 3203,
      "f_end": 3238
    },
    {
      "id": 21,
      "label": "detach_adapter_plate",
      "has_anomaly": false,
      "meta_activity": "none",
      "f_start": 3239,
      "f_end": 3284
    },
    {
      "id": 22,
      "label": "store_adapter_plate",
      "has_anomaly": false,
      "meta_activity": "none",
      "f_start": 3285,
      "f_end": 3306
    },
    {
      "id": 23,
      "label": "remove_rotor_assembly",
      "has_anomaly": false,
      "meta_activity": "none",
      "f_start": 3307,
      "f_end": 3542
    },
    {
      "id": 24,
      "label": "null",
      "has_anomaly": false,
      "meta_activity": "none",
      "f_start": 3543,
      "f_end": 3563
    },
    {
      "id": 25,
      "label": "remove_rotor_assembly",
      "has_anomaly": false,
      "meta_activity": "none",
      "f_start": 3564,
      "f_end": 3641
    },
    {
      "id": 26,
      "label": "store_rotor_assembly",
      "has_anomaly": false,
      "meta_activity": "none",
      "f_start": 3642,
      "f_end": 3666
    },
    {
      "id": 27,
      "label": "remove_rotor_assembly",
      "has_anomaly": false,
      "meta_activity": "none",
      "f_start": 3667,
      "f_end": 3864
    },
    {
      "id": 28,
      "label": "null",
      "has_anomaly": false,
      "meta_activity": "none",
      "f_start": 3865,
      "f_end": 3884
    },
    {
      "id": 29,
      "label": "remove_rotor_assembly",
      "has_anomaly": false,
      "meta_activity": "none",
      "f_start": 3885,
      "f_end": 4081
    },
    {
      "id": 30,
      "label": "null",
      "has_anomaly": false,
      "meta_activity": "none",
      "f_start": 4082,
      "f_end": 4102
    },
    {
      "id": 31,
      "label": "remove_rotor_assembly",
      "has_anomaly": false,
      "meta_activity": "none",
      "f_start": 4103,
      "f_end": 4130
    },
    {
      "id": 32,
      "label": "store_rotor_assembly",
      "has_anomaly": false,
      "meta_activity": "none",
      "f_start": 4131,
      "f_end": 4153
    },
    {
      "id": 33,
      "label": "store_gearbox_housing",
      "has_anomaly": false,
      "meta_activity": "none",
      "f_start": 4154,
      "f_end": 4184
    },
    {
      "id": 34,
      "label": "store_rotor_assembly",
      "has_anomaly": false,
      "meta_activity": "none",
      "f_start": 4185,
      "f_end": 4227
    }
  ],
  "labels": [
    {
      "id": 1,
      "name": "start_angle_grinder_assembly"
    },
    {
      "id": 2,
      "name": "unscrew_anti_vibration_handle"
    },
    {
      "id": 3,
      "name": "store_anti_vibration_handle"
    },
    {
      "id": 4,
      "name": "remove_locking_lever_assembly"
    },
    {
      "id": 5,
      "name": "store_locking_lever_assembly"
    },
    {
      "id": 6,
      "name": "extract_bearing_plate_assembly"
    },
    {
      "id": 7,
      "name": "store_bearing_plate_assembly"
    },
    {
      "id": 8,
      "name": "detach_adapter_plate"
    },
    {
      "id": 9,
      "name": "remove_rotor_assembly"
    },
    {
      "id": 10,
      "name": "store_rotor_assembly"
    },
    {
      "id": 11,
      "name": "store_gearbox_housing"
    },
    {
      "id": 12,
      "name": "store_adapter_plate"
    },
    {
      "id": 0,
      "name": "null"
    },
    {
      "id": 13,
      "name": "retrieve_gearbox_housing"
    },
    {
      "id": 14,
      "name": "retrieve_rotor_assembly"
    },
    {
      "id": 15,
      "name": "install_rotor_assembly"
    },
    {
      "id": 16,
      "name": "attach_adapter_plate"
    },
    {
      "id": 17,
      "name": "retrieve_adapter_plate"
    },
    {
      "id": 18,
      "name": "retrieve_anti_vibration_handle"
    },
    {
      "id": 19,
      "name": "retrieve_bearing_plate_assembly"
    },
    {
      "id": 20,
      "name": "insert_bearing_plate_assembly"
    },
    {
      "id": 21,
      "name": "retrieve_locking_lever_assembly"
    },
    {
      "id": 22,
      "name": "install_locking_lever_assembly"
    },
    {
      "id": 23,
      "name": "screw_on_anti_vibration_handle"
    },
    {
      "id": 24,
      "name": "store_tool"
    },
    {
      "id": 25,
      "name": "finish_angle_grinder_assembly"
    }
  ]
}