{
  "video_id": "20250408_1407_color_ego_sync_clipped",
  "view": "ego",
  "view_start": 0,
  "view_end": 4272,
  "segments": [
    {
      "id": 0,
      "label": "retrieve_gearbox_housing",
      "has_anomaly": false,
      "meta_activity": "none",
      "f_start": 0,
      "f_end": 23
    },
    {
      "id": 1,
      "label": "retrieve_rotor_assembly",
      "has_anomaly": false,
      "meta_activity": "none",
      "f_start": 24,
      "f_end": 53
    },
    {
      "id": 2,
      "label": "install_rotor_assembly",
      "has_anomaly": false,
      "meta_activity": "none",
      "f_start": 54,
      "f_end": 134
    },
    {
      "id": 3,
      "label": "retrieve_adapter_plate",
      "has_anomaly": false,
      "meta_activity": "none",
      "f_start": 135,
      "f_end": 182
    },
    {
      "id": 4,
      "label": "detach_adapter_plate",
      "has_anomaly": false,
      "meta_activity": "none",
      "f_start": 183,
      "f_end": 255
    },
    {
      "id": 5,
      "label": "retrieve_rotor_assembly",
      "has_anomaly": false,
      "meta_activity": "none",
      "f_start": 256,
      "f_end": 306
    },
    {
      "id": 6,
      "label": "install_rotor_assembly",
      "has_anomaly": false,
      "meta_activity": "none",
      "f_start": 307,
      "f_end": 1241
    },
    {
      "id": 7,
      "label": "store_tool",
      "has_anomaly": false,
      "meta_activity": "none",
      "f_start": 1242,
      "f_end": 1266
    },
    {
      "id": 8,
      "label": "attach_adapter_plate",
      "has_anomaly": false,
      "meta_activity": "none",
      "f_start": 1267,
      "f_end": 1329
    },
    {
      "id": 9,
      "label": "retrieve_adapter_plate",
      "has_anomaly": false,
      "meta_activity": "none",
      "f_start": 1330,
      "f_end": 1356
    },
    {
      "id": 10,
      "label": "attach_adapter_plate",
      "has_anomaly": false,
      "meta_activity": "none",
      "f_start": 1357,
      "f_end": 1406
    },
    {
      "id": 11,
      "label": "retrieve_adapter_plate",
      "has_anomaly": false,
      "meta_activity": "none",
      "f_start": 1407,
      "f_end": 1457
    },
    {
      "id": 12,
      "label": "attach_adapter_plate",
      "has_anomaly": false,
      "meta_activity": "none",
      "f_start": 1458,
      "f_end": 1517
    },
    {
      "id": 13,
      "label": "retrieve_adapter_plate",
      "has_anomaly": false,
      "meta_activity": "none",
      "f_start": 1518,
      "f_end": 1551
    },
    {
      "id": 14,
      "label": "attach_adapter_plate",
      "has_anomaly": false,
      "meta_activity": "none",
      "f_start": 1551,
      "f_end": 2035
    },
    {
      "id": 15,
      "label": "null",
      "has_anomaly": false,
      "meta_activity": "none",
      "f_start": 2036,
      "f_end": 2060
    },
    {
      "id": 16,
      "label": "retrieve_adapter_plate",
      "has_anomaly": false,
      "meta_activity": "none",
      "f_start": 2061,
      "f_end": 2093
    },
    {
      "id": 17,
      "label": "attach_adapter_plate",
      "has_anomaly": false,
      "meta_activity": "none",
      "f_start": 2094,
      "f_end": 2588
    },
    {
      "id": 18,
      "label": "store_tool",
      "has_anomaly": false,
      "meta_activity": "none",
      "f_start": 2589,
      "f_end": 2615
    },
    {
      "id": 19,
      "label": "retrieve_bearing_plate_assembly",
      "has_anomaly": false,
      "meta_activity": "none",
      "f_start": 2616,
      "f_end": 2664
    },
    {
      "id": 20,
      "label": "insert_bearing_plate_assembly",
      "has_anomaly": false,
      "meta_activity": "none",
      "f_start": 2664,
      "f_end": 2726
    },
    {
      "id": 21,
      "label": "null",
      "has_anomaly": false,
      "meta_activity": "none",
      "f_start": 2727,
      "f_end": 2743
    },
    {
      "id": 22,
      "label": "retrieve_bearing_plate_assembly",
      "has_anomaly": false,
      "meta_activity": "none",
      "f_start": 2743,
      "f_end": 2778
    },
    {
      "id": 23,
      "label": "insert_bearing_plate_assembly",
      "has_anomaly": false,
      "meta_activity": "none",
      "f_start": 2779,
      "f_end": 3440
    },
    {
      "id": 24,
      "label": "retrieve_locking_lever_assembly",
      "has_anomaly": false,
      "meta_activity": "none",
      "f_start": 3440,
      "f_end": 3524
    },
    {
      "id": 25,
      "label": "install_locking_lever_assembly",
      "has_anomaly": false,
      "meta_activity": "none",
      "f_start": 3525,
      "f_end": 3998
    },
    {
      "id": 26,
      "label": "store_tool",
      "has_anomaly": false,
      "meta_activity": "none",
      "f_start": 3999,
      "f_end": 4019
    },
    {
      "id": 27,
      "label": "retrieve_anti_vibration_handle",
      "has_anomaly": false,
      "meta_activity": "none",
      "f_start": 4020,
      "f_end": 4063
    },
    {
      "id": 28,
      "label": "screw_on_anti_vibration_handle",
      "has_anomaly": false,
      "meta_activity": "none",
      "f_start": 4064,
      "f_end": 4206
    },
    {
      "id": 29,
      "label": "finish_angle_grinder_assembly",
      "has_anomaly": false,
      "meta_activity": "none",
      "f_start": 4207,
      "f_end": 4242
    },
    {
      "id": 30,
      "label": "null",
      "has_anomaly": false,
      "meta_activity": "none",
      "f_start": 4243,
      "f_end": 4272
    }
  ],
  "labels": [
    {
      "id": 1,
      "name": "start_angle_grinder_assembly"
    },
    {
      "id": 2,
      "name": "unscrew_anti_vibration_handle"
    },
    {
      "id": 3,
      "name": "store_anti_vibration_handle"
    },
    {
      "id": 4,
      "name": "remove_locking_lever_assembly"
    },
    {
      "id": 5,
      "name": "store_locking_lever_assembly"
    },
    {
      "id": 6,
      "name": "extract_bearing_plate_assembly"
    },
    {
      "id": 7,
      "name": "store_bearing_plate_assembly"
    },
    {
      "id": 8,
      "name": "detach_adapter_plate"
    },
    {
      "id": 9,
      "name": "remove_rotor_assembly"
    },
    {
      "id": 10,
      "name": "store_rotor_assembly"
    },
    {
      "id": 11,
      "name": "store_gearbox_housing"
    },
    {
      "id": 12,
      "name": "store_adapter_plate"
    },
    {
      "id": 0,
      "name": "null"
    },
    {
      "id": 13,
      "name": "retrieve_gearbox_housing"
    },
    {
      "id": 14,
      "name": "retrieve_rotor_assembly"
    },
    {
      "id": 15,
      "name": "install_rotor_assembly"
    },
    {
      "id": 16,
      "name": "attach_adapter_plate"
    },
    {
      "id": 17,
      "name": "retrieve_adapter_plate"
    },
    {
      "id": 18,
      "name": "retrieve_anti_vibration_handle"
    },
    {
      "id": 19,
      "name": "retrieve_bearing_plate_assembly"
    },
    {
      "id": 20,
      "name": "insert_bearing_plate_assembly"
    },
    {
      "id": 21,
      "name": "retrieve_locking_lever_assembly"
    },
    {
      "id": 22,
      "name": "install_locking_lever_assembly"
    },
    {
      "id": 23,
      "name": "screw_on_anti_vibration_handle"
    },
    {
      "id": 24,
      "name": "store_tool"
    },
    {
      "id": 25,
      "name": "finish_angle_grinder_assembly"
    }
  ]
}