{
  "video_id": "20250414_1454_color_front_clipped",
  "view": "front",
  "view_start": 0,
  "view_end": 6711,
  "segments": [
    {
      "id": 0,
      "label": "retrieve_gearbox_housing",
      "has_anomaly": false,
      "meta_activity": "none",
      "f_start": 0,
      "f_end": 81
    },
    {
      "id": 1,
      "label": "retrieve_rotor_assembly",
      "has_anomaly": false,
      "meta_activity": "none",
      "f_start": 82,
      "f_end": 141
    },
    {
      "id": 2,
      "label": "install_rotor_assembly",
      "has_anomaly": false,
      "meta_activity": "none",
      "f_start": 142,
      "f_end": 190
    },
    {
      "id": 3,
      "label": "retrieve_rotor_assembly",
      "has_anomaly": false,
      "meta_activity": "none",
      "f_start": 191,
      "f_end": 231
    },
    {
      "id": 4,
      "label": "install_rotor_assembly",
      "has_anomaly": false,
      "meta_activity": "none",
      "f_start": 232,
      "f_end": 795
    },
    {
      "id": 5,
      "label": "retrieve_rotor_assembly",
      "has_anomaly": false,
      "meta_activity": "none",
      "f_start": 796,
      "f_end": 874
    },
    {
      "id": 6,
      "label": "install_rotor_assembly",
      "has_anomaly": false,
      "meta_activity": "none",
      "f_start": 875,
      "f_end": 923
    },
    {
      "id": 7,
      "label": "null",
      "has_anomaly": false,
      "meta_activity": "none",
      "f_start": 924,
      "f_end": 969
    },
    {
      "id": 8,
      "label": "install_rotor_assembly",
      "has_anomaly": false,
      "meta_activity": "none",
      "f_start": 970,
      "f_end": 1837
    },
    {
      "id": 9,
      "label": "null",
      "has_anomaly": false,
      "meta_activity": "none",
      "f_start": 1838,
      "f_end": 1938
    },
    {
      "id": 10,
      "label": "retrieve_adapter_plate",
      "has_anomaly": false,
      "meta_activity": "none",
      "f_start": 1939,
      "f_end": 2014
    },
    {
      "id": 11,
      "label": "attach_adapter_plate",
      "has_anomaly": false,
      "meta_activity": "none",
      "f_start": 2015,
      "f_end": 2095
    },
    {
      "id": 12,
      "label": "retrieve_adapter_plate",
      "has_anomaly": false,
      "meta_activity": "none",
      "f_start": 2096,
      "f_end": 2152
    },
    {
      "id": 13,
      "label": "attach_adapter_plate",
      "has_anomaly": false,
      "meta_activity": "none",
      "f_start": 2153,
      "f_end": 2343
    },
    {
      "id": 14,
      "label": "retrieve_adapter_plate",
      "has_anomaly": false,
      "meta_activity": "none",
      "f_start": 2344,
      "f_end": 2406
    },
    {
      "id": 15,
      "label": "attach_adapter_plate",
      "has_anomaly": false,
      "meta_activity": "none",
      "f_start": 2407,
      "f_end": 2821
    },
    {
      "id": 16,
      "label": "retrieve_adapter_plate",
      "has_anomaly": false,
      "meta_activity": "none",
      "f_start": 2822,
      "f_end": 2897
    },
    {
      "id": 17,
      "label": "attach_adapter_plate",
      "has_anomaly": false,
      "meta_activity": "none",
      "f_start": 2898,
      "f_end": 3058
    },
    {
      "id": 18,
      "label": "retrieve_adapter_plate",
      "has_anomaly": false,
      "meta_activity": "none",
      "f_start": 3059,
      "f_end": 3131
    },
    {
      "id": 19,
      "label": "attach_adapter_plate",
      "has_anomaly": false,
      "meta_activity": "none",
      "f_start": 3132,
      "f_end": 3521
    },
    {
      "id": 20,
      "label": "retrieve_bearing_plate_assembly",
      "has_anomaly": false,
      "meta_activity": "none",
      "f_start": 3522,
      "f_end": 3575
    },
    {
      "id": 21,
      "label": "insert_bearing_plate_assembly",
      "has_anomaly": false,
      "meta_activity": "none",
      "f_start": 3576,
      "f_end": 3747
    },
    {
      "id": 22,
      "label": "retrieve_bearing_plate_assembly",
      "has_anomaly": false,
      "meta_activity": "none",
      "f_start": 3748,
      "f_end": 3834
    },
    {
      "id": 23,
      "label": "insert_bearing_plate_assembly",
      "has_anomaly": false,
      "meta_activity": "none",
      "f_start": 3835,
      "f_end": 5037
    },
    {
      "id": 24,
      "label": "retrieve_locking_lever_assembly",
      "has_anomaly": false,
      "meta_activity": "none",
      "f_start": 5038,
      "f_end": 5266
    },
    {
      "id": 25,
      "label": "install_locking_lever_assembly",
      "has_anomaly": false,
      "meta_activity": "none",
      "f_start": 5267,
      "f_end": 6226
    },
    {
      "id": 26,
      "label": "store_tool",
      "has_anomaly": false,
      "meta_activity": "none",
      "f_start": 6227,
      "f_end": 6258
    },
    {
      "id": 27,
      "label": "retrieve_anti_vibration_handle",
      "has_anomaly": false,
      "meta_activity": "none",
      "f_start": 6259,
      "f_end": 6321
    },
    {
      "id": 28,
      "label": "screw_on_anti_vibration_handle",
      "has_anomaly": false,
      "meta_activity": "none",
      "f_start": 6322,
      "f_end": 6601
    },
    {
      "id": 29,
      "label": "finish_angle_grinder_assembly",
      "has_anomaly": false,
      "meta_activity": "none",
      "f_start": 6602,
      "f_end": 6711
    }
  ],
  "labels": [
    {
      "id": 1,
      "name": "start_angle_grinder_assembly"
    },
    {
      "id": 2,
      "name": "unscrew_anti_vibration_handle"
    },
    {
      "id": 3,
      "name": "store_anti_vibration_handle"
    },
    {
      "id": 4,
      "name": "remove_locking_lever_assembly"
    },
    {
      "id": 5,
      "name": "store_locking_lever_assembly"
    },
    {
      "id": 6,
      "name": "extract_bearing_plate_assembly"
    },
    {
      "id": 7,
      "name": "store_bearing_plate_assembly"
    },
    {
      "id": 8,
      "name": "detach_adapter_plate"
    },
    {
      "id": 9,
      "name": "remove_rotor_assembly"
    },
    {
      "id": 10,
      "name": "store_rotor_assembly"
    },
    {
      "id": 11,
      "name": "store_gearbox_housing"
    },
    {
      "id": 12,
      "name": "store_adapter_plate"
    },
    {
      "id": 0,
      "name": "null"
    },
    {
      "id": 13,
      "name": "retrieve_gearbox_housing"
    },
    {
      "id": 14,
      "name": "retrieve_rotor_assembly"
    },
    {
      "id": 15,
      "name": "install_rotor_assembly"
    },
    {
      "id": 16,
      "name": "attach_adapter_plate"
    },
    {
      "id": 17,
      "name": "retrieve_adapter_plate"
    },
    {
      "id": 18,
      "name": "retrieve_anti_vibration_handle"
    },
    {
      "id": 19,
      "name": "retrieve_bearing_plate_assembly"
    },
    {
      "id": 20,
      "name": "insert_bearing_plate_assembly"
    },
    {
      "id": 21,
      "name": "retrieve_locking_lever_assembly"
    },
    {
      "id": 22,
      "name": "install_locking_lever_assembly"
    },
    {
      "id": 23,
      "name": "screw_on_anti_vibration_handle"
    },
    {
      "id": 24,
      "name": "store_tool"
    },
    {
      "id": 25,
      "name": "finish_angle_grinder_assembly"
    }
  ]
}